py4logistic_regression/__init__.py
py4logistic_regression/regression.py
py4logistic_regression-0.0.4.dist-info/METADATA
py4logistic_regression-0.0.4.dist-info/WHEEL
py4logistic_regression-0.0.4.dist-info/top_level.txt
py4logistic_regression-0.0.4.dist-info/RECORD
