Metadata-Version: 2.1
Name: py4logistic-regression
Version: 0.0.4
Summary: Logistic Regression Python Library
Home-page: https://github.com/luthfi118/py4logistic_regression
Author: Mgs. M. Luthfi Ramadhan
Author-email: luthfir96@gmail.com
License: UNKNOWN
Platform: UNKNOWN
Classifier: Programming Language :: Python :: 3
Classifier: License :: OSI Approved :: MIT License
Classifier: Operating System :: OS Independent
Requires-Python: >=3.7
Requires-Dist: numpy
